github_search_engine/__init__.py
github_search_engine/_api/__init__.py
github_search_engine/_api/api.py
github_search_engine/_cli/__init__.py
github_search_engine/_cli/commands/__init__.py
github_search_engine/_cli/commands/api_command.py
github_search_engine/_cli/commands/index_command.py
github_search_engine/_cli/commands/search_command.py
github_search_engine/_cli/commands/utils.py
github_search_engine/cli.py
github_search_engine/clients/__init__.py
github_search_engine/clients/github_client_manager.py
github_search_engine/clients/ollama_client_manager.py
github_search_engine/github_search_engine.py
github_search_engine-0.3.0.dist-info/METADATA
github_search_engine-0.3.0.dist-info/WHEEL
github_search_engine-0.3.0.dist-info/entry_points.txt
github_search_engine-0.3.0.dist-info/RECORD
