Metadata-Version: 2.1
Name: Github-Search-Engine
Version: 0.3.0
Summary: Search through github issues and PRs like never before.
Home-page: https://github.com/sachahu1/Github-Search-Engine
Author: Sacha hu
Author-email: hu.sacha.ai@gmail.com
Maintainer: Sacha hu
Maintainer-email: hu.sacha.ai@gmail.com
Requires-Python: >=3.10,<3.14
Classifier: Programming Language :: Python :: 3
Classifier: Programming Language :: Python :: 3.10
Classifier: Programming Language :: Python :: 3.11
Classifier: Programming Language :: Python :: 3.12
Classifier: Programming Language :: Python :: 3.13
Provides-Extra: api
Provides-Extra: cpu
Provides-Extra: gpu
Requires-Dist: chevron (>=0.14.0,<0.15.0)
Requires-Dist: cleo (>=2.1.0,<3.0.0)
Requires-Dist: fastapi[standard] (>=0.115.5,<0.116.0) ; extra == "api"
Requires-Dist: githubkit (>=0.11.14,<0.12.0)
Requires-Dist: ollama (>=0.4.0,<0.5.0)
Requires-Dist: onnxruntime-gpu (>=1.19.2,<2.0.0) ; extra == "gpu"
Requires-Dist: python-dotenv (>=1.0.1,<2.0.0)
Requires-Dist: qdrant-client[fastembed-gpu] (>=1.12.1,<2.0.0) ; extra == "gpu"
Requires-Dist: qdrant-client[fastembed] (>=1.12.1,<2.0.0) ; extra == "cpu"
Project-URL: Documentation, https://www.sachahu.com/docs/Github-Search-Engine/latest/index.html
Project-URL: Repository, https://github.com/sachahu1/Github-Search-Engine
